biome/__init__.py
biome-0.1.3.dist-info/DESCRIPTION.rst
biome-0.1.3.dist-info/METADATA
biome-0.1.3.dist-info/RECORD
biome-0.1.3.dist-info/WHEEL
biome-0.1.3.dist-info/metadata.json
biome-0.1.3.dist-info/top_level.txt
